mcp_server_rednote/__init__.py
mcp_server_rednote/__main__.py
mcp_server_rednote/browser.py
mcp_server_rednote/server.py
mcp_server_rednote/settings.py
mcp_server_rednote-0.1.4.dist-info/METADATA
mcp_server_rednote-0.1.4.dist-info/WHEEL
mcp_server_rednote-0.1.4.dist-info/entry_points.txt
mcp_server_rednote-0.1.4.dist-info/RECORD
